imutils/__init__.py
imutils/contours.py
imutils/convenience.py
imutils/encodings.py
imutils/meta.py
imutils/object_detection.py
imutils/paths.py
imutils/perspective.py
imutils/text.py
imutils/face_utils/__init__.py
imutils/face_utils/facealigner.py
imutils/face_utils/helpers.py
imutils/feature/__init__.py
imutils/feature/dense.py
imutils/feature/factories.py
imutils/feature/gftt.py
imutils/feature/harris.py
imutils/feature/helpers.py
imutils/feature/rootsift.py
imutils/io/__init__.py
imutils/io/tempfile.py
imutils/video/__init__.py
imutils/video/count_frames.py
imutils/video/filevideostream.py
imutils/video/fps.py
imutils/video/pivideostream.py
imutils/video/videostream.py
imutils/video/webcamvideostream.py
linus_imutils-0.5.4.data/scripts/range-detector
linus_imutils-0.5.4.dist-info/LICENSE.txt
linus_imutils-0.5.4.dist-info/METADATA
linus_imutils-0.5.4.dist-info/WHEEL
linus_imutils-0.5.4.dist-info/top_level.txt
linus_imutils-0.5.4.dist-info/RECORD
