Metadata-Version: 1.0
Name: linus_imutils
Version: 0.5.4
Summary: A series of convenience functions to make basic image processing functions such as translation, rotation, resizing, skeletonization, displaying Matplotlib images, sorting contours, detecting edges, and much more easier with OpenCV and both Python 2.7 and Python 3.
Home-page: https://github.com/lamhoangtung/imutils
Author: Adrian Rosebrock
Author-email: adrian@pyimagesearch.com
License: UNKNOWN
Keywords: computer vision,image processing,opencv,matplotlib
Platform: UNKNOWN
